CYPHER_STT/__init__.py
cypher_stt-1.0.0.dist-info/METADATA
cypher_stt-1.0.0.dist-info/WHEEL
cypher_stt-1.0.0.dist-info/top_level.txt
cypher_stt-1.0.0.dist-info/RECORD
