Metadata-Version: 2.4
Name: CYPHER_STT
Version: 1.0.0
Summary:  This is a Speech To Text package created by Ameer Omar
Author: Ameer Omar
Author-email: ameershaaban2004@gmail.com
Dynamic: author
Dynamic: author-email
Dynamic: summary
